BianxieGaozhiliangDaimaGaishanPythonChengxuDe91GeJianyi/README.md
BianxieGaozhiliangDaimaGaishanPythonChengxuDe91GeJianyi/__init__.py
BianxieGaozhiliangDaimaGaishanPythonChengxuDe91GeJianyi/__main__.py
BianxieGaozhiliangDaimaGaishanPythonChengxuDe91GeJianyi/file.epub
BianxieGaozhiliangDaimaGaishanPythonChengxuDe91GeJianyi/index.html
BianxieGaozhiliangDaimaGaishanPythonChengxuDe91GeJianyi/css/__init__.py
BianxieGaozhiliangDaimaGaishanPythonChengxuDe91GeJianyi/css/annotations.css
BianxieGaozhiliangDaimaGaishanPythonChengxuDe91GeJianyi/css/main.css
BianxieGaozhiliangDaimaGaishanPythonChengxuDe91GeJianyi/css/normalize.css
BianxieGaozhiliangDaimaGaishanPythonChengxuDe91GeJianyi/css/popup.css
BianxieGaozhiliangDaimaGaishanPythonChengxuDe91GeJianyi/font/__init__.py
BianxieGaozhiliangDaimaGaishanPythonChengxuDe91GeJianyi/font/fontello.eot
BianxieGaozhiliangDaimaGaishanPythonChengxuDe91GeJianyi/font/fontello.svg
BianxieGaozhiliangDaimaGaishanPythonChengxuDe91GeJianyi/font/fontello.ttf
BianxieGaozhiliangDaimaGaishanPythonChengxuDe91GeJianyi/font/fontello.woff
BianxieGaozhiliangDaimaGaishanPythonChengxuDe91GeJianyi/img/__init__.py
BianxieGaozhiliangDaimaGaishanPythonChengxuDe91GeJianyi/img/annotator-glyph-sprite.png
BianxieGaozhiliangDaimaGaishanPythonChengxuDe91GeJianyi/img/annotator-icon-sprite.png
BianxieGaozhiliangDaimaGaishanPythonChengxuDe91GeJianyi/img/apple-touch-icon.png
BianxieGaozhiliangDaimaGaishanPythonChengxuDe91GeJianyi/img/cancelfullscreen.png
BianxieGaozhiliangDaimaGaishanPythonChengxuDe91GeJianyi/img/close.png
BianxieGaozhiliangDaimaGaishanPythonChengxuDe91GeJianyi/img/fullscreen.png
BianxieGaozhiliangDaimaGaishanPythonChengxuDe91GeJianyi/img/loader.gif
BianxieGaozhiliangDaimaGaishanPythonChengxuDe91GeJianyi/img/menu-icon.png
BianxieGaozhiliangDaimaGaishanPythonChengxuDe91GeJianyi/img/save.png
BianxieGaozhiliangDaimaGaishanPythonChengxuDe91GeJianyi/img/saved.png
BianxieGaozhiliangDaimaGaishanPythonChengxuDe91GeJianyi/img/settings-s.png
bianxie_gaozhiliang_daima_gaishan_python_chengxu_de_91_ge_jianyi-2024.3.4.0.dist-info/METADATA
bianxie_gaozhiliang_daima_gaishan_python_chengxu_de_91_ge_jianyi-2024.3.4.0.dist-info/WHEEL
bianxie_gaozhiliang_daima_gaishan_python_chengxu_de_91_ge_jianyi-2024.3.4.0.dist-info/entry_points.txt
bianxie_gaozhiliang_daima_gaishan_python_chengxu_de_91_ge_jianyi-2024.3.4.0.dist-info/top_level.txt
bianxie_gaozhiliang_daima_gaishan_python_chengxu_de_91_ge_jianyi-2024.3.4.0.dist-info/RECORD
